c42eventextractor/__init__.py
c42eventextractor/__version__.py
c42eventextractor/common.py
c42eventextractor/compat.py
c42eventextractor/extraction_handlers.py
c42eventextractor/extractors.py
c42eventextractor/maps.py
c42eventextractor/logging/__init__.py
c42eventextractor/logging/formatters.py
c42eventextractor/logging/handlers.py
c42eventextractor-0.4.1.dist-info/LICENSE.md
c42eventextractor-0.4.1.dist-info/METADATA
c42eventextractor-0.4.1.dist-info/WHEEL
c42eventextractor-0.4.1.dist-info/top_level.txt
c42eventextractor-0.4.1.dist-info/RECORD
